{
    "navigationBarBackgroundColor": "#07c160",
    "backgroundTextStyle": "dark",
    "navigationBarTextStyle": "white",
    "navigationBarTitleText": "我的购物车",
    "usingComponents": {
        "t-input": "tdesign-miniprogram/input/input",
        "t-textarea": "tdesign-miniprogram/textarea/textarea",
        "t-button": "tdesign-miniprogram/button/button",
        "t-checkbox-group": "tdesign-miniprogram/checkbox-group/checkbox-group",
        "t-icon": "tdesign-miniprogram/icon/icon",
        "t-checkbox": "tdesign-miniprogram/checkbox/checkbox"
    }
}